sc/toolbox/__init__.py
sc/toolbox/_main/__init__.py
sc/toolbox/_main/archive/__init__.py
sc/toolbox/_main/archive/hashlink.py
sc/toolbox/_main/image/__init__.py
sc/toolbox/_main/image/border.py
sc/toolbox/click/help.py
sc/toolbox/config/__init__.py
sc/toolbox/config/base.py
sc/toolbox/config/image_border.py
sc/toolbox/exiftool.py
sc/toolbox/logging.py
sapphiccode_toolbox-0.1.0.dist-info/LICENSE
sapphiccode_toolbox-0.1.0.dist-info/METADATA
sapphiccode_toolbox-0.1.0.dist-info/WHEEL
sapphiccode_toolbox-0.1.0.dist-info/entry_points.txt
sapphiccode_toolbox-0.1.0.dist-info/RECORD
