Metadata-Version: 2.1
Name: sapphiccode-toolbox
Version: 0.1.0
Summary: 
License: EUPL-1.2
Author: Cassandra
Author-email: git@sapphicco.de
Requires-Python: >=3.10,<4.0
Classifier: License :: OSI Approved :: European Union Public Licence 1.2 (EUPL 1.2)
Classifier: Programming Language :: Python :: 3
Classifier: Programming Language :: Python :: 3.10
Classifier: Programming Language :: Python :: 3.11
Requires-Dist: click (>=8.1.6,<9.0.0)
Requires-Dist: pillow (>=10,<11)
Requires-Dist: pydantic (>=2,<3)
Requires-Dist: pyyaml (>=6.0.1,<7.0.0)
Requires-Dist: rich (>=13.5.2,<14.0.0)
Requires-Dist: structlog (>=23.1.0)
Requires-Dist: tqdm (>=4.66.1,<5.0.0)
